README.rst
setup.cfg
setup.py
logipy/__init__.py
logipy/logi_arx.py
logipy/logi_led.py
logipy.egg-info/PKG-INFO
logipy.egg-info/SOURCES.txt
logipy.egg-info/dependency_links.txt
logipy.egg-info/top_level.txt