Metadata-Version: 1.1
Name: logipy
Version: 1.2.1
Summary: A simple python wrapper for Logitech G's LED and Arx SDKs.
Home-page: http://gaming.logitech.com/en-us/developers
Author: Tom Lambert
Author-email: devtechsupport@logitech.com
License: MIT
Download-URL: https://github.com/Logitech/logiPy/tarball/master
Keywords: logi,logipy,Logitech,LogitechG,LED,Arx,LGS,Logitech Gaming Software
Platform: UNKNOWN
Classifier: Development Status :: 5 - Production/Stable
Classifier: Topic :: Software Development :: Libraries
